Metadata-Version: 2.1
Name: ss-acryl-datahub
Version: 0.9.6.4.post9
Summary: A CLI to work with DataHub metadata
Home-page: https://datahubproject.io/
License: Apache License 2.0
Project-URL: Documentation, https://datahubproject.io/docs/
Project-URL: Source, https://github.com/datahub-project/datahub
Project-URL: Changelog, https://github.com/datahub-project/datahub/releases
Platform: UNKNOWN
Classifier: Development Status :: 5 - Production/Stable
Classifier: Programming Language :: Python
Classifier: Programming Language :: Python :: 3
Classifier: Programming Language :: Python :: 3 :: Only
Classifier: Programming Language :: Python :: 3.7
Classifier: Programming Language :: Python :: 3.8
Classifier: Programming Language :: Python :: 3.9
Classifier: Programming Language :: Python :: 3.10
Classifier: Intended Audience :: Developers
Classifier: Intended Audience :: Information Technology
Classifier: Intended Audience :: System Administrators
Classifier: License :: OSI Approved
Classifier: License :: OSI Approved :: Apache Software License
Classifier: Operating System :: Unix
Classifier: Operating System :: POSIX :: Linux
Classifier: Environment :: Console
Classifier: Environment :: MacOS X
Classifier: Topic :: Software Development
Requires-Python: >=3.7
Provides-Extra: base
Provides-Extra: datahub-kafka
Provides-Extra: datahub-rest
Provides-Extra: datahub-lite
Provides-Extra: airflow
Provides-Extra: circuit-breaker
Provides-Extra: great-expectations
Provides-Extra: athena
Provides-Extra: azure-ad
Provides-Extra: bigquery
Provides-Extra: bigquery-beta
Provides-Extra: clickhouse
Provides-Extra: clickhouse-usage
Provides-Extra: datahub-lineage-file
Provides-Extra: datahub-business-glossary
Provides-Extra: delta-lake
Provides-Extra: dbt
Provides-Extra: dbt-cloud
Provides-Extra: druid
Provides-Extra: elasticsearch
Provides-Extra: feast
Provides-Extra: glue
Provides-Extra: hana
Provides-Extra: hive
Provides-Extra: iceberg
Provides-Extra: kafka
Provides-Extra: kafka-connect
Provides-Extra: ldap
Provides-Extra: looker
Provides-Extra: lookml
Provides-Extra: metabase
Provides-Extra: mode
Provides-Extra: mongodb
Provides-Extra: mssql
Provides-Extra: mssql-odbc
Provides-Extra: mysql
Provides-Extra: mariadb
Provides-Extra: okta
Provides-Extra: oracle
Provides-Extra: postgres
Provides-Extra: presto
Provides-Extra: presto-on-hive
Provides-Extra: pulsar
Provides-Extra: redash
Provides-Extra: redshift
Provides-Extra: redshift-usage
Provides-Extra: s3
Provides-Extra: sagemaker
Provides-Extra: salesforce
Provides-Extra: snowflake
Provides-Extra: snowflake-beta
Provides-Extra: sqlalchemy
Provides-Extra: superset
Provides-Extra: tableau
Provides-Extra: trino
Provides-Extra: starburst-trino-usage
Provides-Extra: nifi
Provides-Extra: powerbi
Provides-Extra: powerbi-report-server
Provides-Extra: vertica
Provides-Extra: unity-catalog
Provides-Extra: all
Provides-Extra: dev
Provides-Extra: integration-tests
